copycurse/__init__.py
copycurse/__main__.py
copycurse-0.0.2.dist-info/LICENSE
copycurse-0.0.2.dist-info/METADATA
copycurse-0.0.2.dist-info/WHEEL
copycurse-0.0.2.dist-info/entry_points.txt
copycurse-0.0.2.dist-info/top_level.txt
copycurse-0.0.2.dist-info/RECORD
